LICENSE
MANIFEST.in
README.md
README.rst
requirements.txt
setup.py
datahub/__init__.py
datahub/core.py
datahub/exceptions.py
datahub/implement.py
datahub/rest.py
datahub/version.py
datahub/auth/__init__.py
datahub/auth/aliyun_account.py
datahub/auth/core.py
datahub/models/__init__.py
datahub/models/compress.py
datahub/models/connector.py
datahub/models/cursor.py
datahub/models/params.py
datahub/models/record.py
datahub/models/results.py
datahub/models/schema.py
datahub/models/shard.py
datahub/models/subscription.py
datahub/models/types.py
datahub/proto/__init__.py
datahub/proto/datahub_record_proto_pb.py
datahub/utils/__init__.py
datahub/utils/codec.py
datahub/utils/constants.py
datahub/utils/converters.py
datahub/utils/validator.py
pydatahub_beta.egg-info/PKG-INFO
pydatahub_beta.egg-info/SOURCES.txt
pydatahub_beta.egg-info/dependency_links.txt
pydatahub_beta.egg-info/requires.txt
pydatahub_beta.egg-info/top_level.txt