Metadata-Version: 1.0
Name: pydatahub-beta
Version: 0.0.6
Summary: Datahub Python SDK
Home-page: https://github.com/aliyun/aliyun-datahub-sdk-python
Author: andy.xs
Author-email: helloworld.xs@foxmail.com
License: Apache License 2.0
Keywords: pydatahub,python,aliyun,datahub,sdk
Platform: UNKNOWN
